CorpFin/Capital.py
CorpFin/Portfolio.py
CorpFin/Security.py
CorpFin/Valuation.py
CorpFin/__init__.py
CorpFin-0.0.0.dist-info/DESCRIPTION.rst
CorpFin-0.0.0.dist-info/METADATA
CorpFin-0.0.0.dist-info/RECORD
CorpFin-0.0.0.dist-info/WHEEL
CorpFin-0.0.0.dist-info/metadata.json
CorpFin-0.0.0.dist-info/top_level.txt
