Metadata-Version: 2.0
Name: CorpFin
Version: 0.0.0
Summary: Corporate Finance functionalities based on SymPy and Theano
Home-page: https://github.com/MBALearnsToCode/CorpFin
Author: Vinh Luong (a.k.a. MBALearnsToCode)
Author-email: MBALearnsToCode@UChicago.edu
License: MIT License
Keywords: corporate finance corp fin financial sympy theano
Platform: UNKNOWN
Requires-Dist: FrozenDict
Requires-Dist: NamedList
Requires-Dist: NumPy
Requires-Dist: Pandas
Requires-Dist: SymPy
Requires-Dist: Theano
